{
  "category": "左門くんはサモナー",
  "items": [
    {
      "id": "73f253fa-0b0d-4117-8497-96d02b72d227",
      "title": "左門くんはサモナー",
      "body": "┌――ｚ\r\n　　　　 　 　　 . -┘　 〔\r\n　　　　　　 　 ′　　 　 　 '，\r\n　　　　　　　 { 　⌒　 ⌒　 }\r\n　 　 　 　 　 ‘.　　 ､ ﾌ　　.′\r\n　　　　　　　　　 ‐---‐",
      "tags": [
        "mlt",
        "左門くんはサモナー"
      ],
      "source": "mlt_v31_7",
      "created_at": "2026-04-14",
      "use_count": 0
    },
    {
      "id": "bf10956e-b1b6-4deb-8c06-b6641bf737c1",
      "title": "左門くんはサモナー",
      "body": "＿＿＿_\r\n　　　/￣￣ヽ´　　　　　｀ヾ⌒＼\r\n　　/　　 　　　　　　　　 　　ヽ 　ヽ\r\n　　|　　 　　　 ｨｰｧ 　　 ｨｰｧ　 | 　|\r\n　　ヽ　 　 　　 ∧ ヽ　　　| _∧　　l　　　　しかしベヒモス\r\n　　　ヽ ＿ﾉ　（__ﾉ 　ヽ 　 |＿人　ﾉ\r\n　　　 　 ヾ 　ヽ　 　 　i 　 |,/ 　）´　　　　意外にもこれをスルー\r\n　 　 　 　 i＼　 ~~⌒丿　ﾉ　　ﾉ\r\n　　　　　　|　｀ー―'く__／ー-'",
      "tags": [
        "mlt",
        "左門くんはサモナー"
      ],
      "source": "mlt_v31_7",
      "created_at": "2026-04-14",
      "use_count": 0
    },
    {
      "id": "e6621515-5ddd-4a99-a788-a98e6f3b812d",
      "title": "左門くんはサモナー",
      "body": "＿＿＿＿＿＿＿＿＿＿\r\n◎　◎　 　　／\r\n　Ｍ 　　　＜　　二度寝するでヤンス！\r\n　Ｗ　　　　　＼＿＿＿＿＿＿＿＿＿＿",
      "tags": [
        "mlt",
        "左門くんはサモナー"
      ],
      "source": "mlt_v31_7",
      "created_at": "2026-04-14",
      "use_count": 0
    },
    {
      "id": "76ffac4b-af53-4b1c-9ce4-f73e3db1120d",
      "title": "左門くんはサモナー",
      "body": ",～'~`～'~`～'~`～'~`～'~`､\r\n◎　◎　 （　不貞寝するでヤンス…　）\r\nＵ o Ｕ　　｀～､_,～､_,～､_,～､_,～､_,～",
      "tags": [
        "mlt",
        "左門くんはサモナー"
      ],
      "source": "mlt_v31_7",
      "created_at": "2026-04-14",
      "use_count": 0
    },
    {
      "id": "50ad40ba-632d-4c16-ba6b-64a6a1146b05",
      "title": "左門くんはサモナー",
      "body": "[差分]\r\n　　r'　　　 　 ﾋ　　　ヒ r'´ だ つ 見　ヽヒ 　　〈　だ つ　ヒ　　ﾋ. -‐-y' の　塩 ほ　｝\r\nヒ　}　　つ　　}ｿ　　__ソ 　 ぜ け ろ 　 )　ソ 　 j　：. け　 iソ　ｆ ｿ　　　　：　 ま ら .ﾉ\r\n　ソ! 　 け 　 ｊ 　 ﾉ 　 　 　 　 も よ 　 }　　　　{　 　 も　 }　　 !　例 あ .：.　み　　}\r\n　　j　　も　　|　 ( 　 あ 　 　　の　　 r'　　　　 ､_ 　 の　ｊ　 　 }　の あ　_　 れ　/\r\n　　! 　 の　　}　 ｝ 　れ　　　　　　　_ﾉ　　　　　　｀…-‐'´ 　　 ､　：　　 ﾉ 　ヽ__ヒ\r\n　　ヽ　 ：　 .ﾉ 　 !. 　が　　}ヽ-‐'¨´　　　　　　　　　　　　　　　 ヽ ＿.ノ　　　　　ｿ\r\n　　　｀ー-'¨　　 ヽ　　：　 ﾉ\r\n　　　　　　　　　　　､__, -'",
      "tags": [
        "mlt",
        "左門くんはサモナー"
      ],
      "source": "mlt_v31_7",
      "created_at": "2026-04-14",
      "use_count": 0
    }
  ]
}